<?xml version="1.0" encoding="utf-8" ?>
<Defs>
	  
	  <GeneDef MayRequire="OskarPotocki.VanillaFactionsExpanded.Core">
		<defName>guy762_Furskin_shortfur</defName>
		<label>short furskin</label>
		<labelShortAdj>furskinned</labelShortAdj>
		<description>Carriers of this gene grow thin fur all over their body, which protects them from cold temperatures. This is otherwise identical to regular furskin, save for the fact it uses the pawn's "skin" color instead.</description>
		<biostatCpx>1</biostatCpx>
		<biostatMet>-1</biostatMet>
		<displayOrderInCategory>776</displayOrderInCategory>
		<displayCategory>guy762_SWparts_Category</displayCategory>
		<iconPath>UI/Icons/Genes/Gene_Furskin</iconPath>
		<iconColor>(255,255,255)</iconColor>
		<!--skinColorOverride>(165,180,190)</skinColorOverride-->
		<forcedHeadTypes>
		  <li>guy762_shortFurskin_Average1</li>
		  <li>guy762_shortFurskin_Average2</li>
		  <li>guy762_shortFurskin_Average3</li>
		  <li>guy762_shortFurskin_Narrow1</li>
		  <li>guy762_shortFurskin_Narrow2</li>
		  <li>guy762_shortFurskin_Narrow3</li>
		  <li>guy762_shortFurskin_Heavy1</li>
		  <li>guy762_shortFurskin_Heavy2</li>
		  <li>guy762_shortFurskin_Heavy3</li>
		  <li>guy762_shortFurskin_Gaunt</li>
		</forcedHeadTypes>
		<beardTagFilter>
		  <whitelist>true</whitelist>
		  <tags>
			<li>BeardLong</li>
			<li>Furskin</li>
		  </tags>
		</beardTagFilter>
		<exclusionTags>
		  <li>HairStyle</li>
		  <li>Fur</li>
		  <li>BeardStyle</li>
		</exclusionTags>
		<statOffsets>
		  <ComfyTemperatureMin>-10</ComfyTemperatureMin>
		</statOffsets>
		<missingGeneRomanceChanceFactor>0.2</missingGeneRomanceChanceFactor>
		<fur>Furskin</fur>
		<skinIsHairColor>false</skinIsHairColor>
		<tattoosVisible>false</tattoosVisible>
		<renderNodeProperties>
		  <li>
			<debugLabel>Fur</debugLabel>
			<nodeClass>PawnRenderNode_Fur</nodeClass>
			<workerClass>PawnRenderNodeWorker_Fur</workerClass>
			<baseLayer>5</baseLayer>
			<rotDrawMode>Fresh, Rotting</rotDrawMode>
			<colorType>Skin</colorType>
			<parentTagDef>Body</parentTagDef>
		  </li>
		</renderNodeProperties>
		<modExtensions>
			<li Class="VanillaGenesExpanded.GeneExtension">
                <useSkinColorForFur>true</useSkinColorForFur>
            </li>
		</modExtensions>
	  </GeneDef>
	  
	 
	  <GeneDef ParentName="GeneTailBase">
		<defName>guy762_Tail_hutt</defName>
		<label>slug tail</label>
		<description>Carriers of this gene grow huge, bulbous tails in place of legs. They aren't very dexterous.</description>
		<iconPath>UI/Icons/Genes/Gene_TailFat</iconPath>
		<iconColor>(0.75, 0.75, 0.75)</iconColor>
		<displayOrderInCategory>785</displayOrderInCategory>
		<displayCategory>guy762_SWparts_Category</displayCategory>
		<statOffsets>
		  <MoveSpeed>-2.7</MoveSpeed>
		</statOffsets>
		<biostatCpx>1</biostatCpx>
		<biostatMet>4</biostatMet>
		<renderNodeProperties>
		  <li>
			<workerClass>PawnRenderNodeWorker_AttachmentBody</workerClass>
			<texPath>Pawn/BodyAttachments/hutt/bp_fat</texPath>
			<colorType>Skin</colorType>
			<overrideMeshSize>(1.2, 1.2)</overrideMeshSize>
			<parentTagDef>Body</parentTagDef>
			<rotDrawMode>Fresh, Rotting</rotDrawMode>
			<useSkinShader>true</useSkinShader>
			<useRottenColor>true</useRottenColor>
			<visibleFacing>
			  <li>East</li>
			  <li>North</li>
			  <li>West</li>
			</visibleFacing>
			<drawData>
			  <scaleOffsetByBodySize>true</scaleOffsetByBodySize>
			  <defaultData>
				<layer>90</layer>
			  </defaultData>
			  <dataNorth>
				<offset>(0, 0.1, -0.6)</offset>
			  </dataNorth>
			  <dataEast>
				<offset>(-0.64, 0.1, 0.01)</offset>
			  </dataEast>
			  <dataWest>
				<offset>(0.64, 0.1, 0.01)</offset>
			  </dataWest>
			</drawData>
		  </li>
		</renderNodeProperties>
		
		<prerequisite>Body_Fat</prerequisite>
		
		<!--modExtensions MayRequire="RedMattis.LamiasAndOtherSnakes">
			<li Class="BetterPrerequisites.GeneExtension">
				<applyBodyHediff>
					<li>
						<hediff MayRequire="OskarPotocki.VanillaFactionsExpanded.Core">BS_Slither</hediff>
					</li>
				</applyBodyHediff>
				<applyPartHediff>
					<li>
						<hediff>LS_SnakeTail</hediff>
						<bodyparts>
							<li>Leg</li>
							<li>Leg</li>
							<li MayRequire="erdelf.HumanoidAlienRaces">BS_SnakeBody</li>
						</bodyparts>
					</li>
				</applyPartHediff>
				<thingDefSwap MayRequire="erdelf.HumanoidAlienRaces">BS_Naga</thingDefSwap>
				<forceThingDefSwap>false</forceThingDefSwap>
				<bodyPosOffset>0.5</bodyPosOffset>
			</li>
		</modExtensions-->
	  </GeneDef>
	  
	  
	  
	  <GeneDef ParentName="GeneTailBase">
		<defName>guy762_BodyAttachment_falleen</defName>
		<label>ridged spine</label>
		<description>Carriers of this gene grow pronounced, ridged spines.</description>
		<iconPath>UI/Icons/Genes/Gene_RidgedSpine</iconPath>
		<iconColor>(0.75, 0.75, 0.75)</iconColor>
		<displayOrderInCategory>785</displayOrderInCategory>
		<displayCategory>guy762_SWparts_Category</displayCategory>
		<renderNodeProperties>
		  <li>
			<workerClass>PawnRenderNodeWorker_AttachmentBody</workerClass>
			<bodyTypeGraphicPaths>
				<Thin>Pawn/BodyAttachments/falleen/ridgedspine_thin</Thin>
				<Female>Pawn/BodyAttachments/falleen/ridgedspine_female</Female>
				<Male>Pawn/BodyAttachments/falleen/ridgedspine_male</Male>
				<Hulk>Pawn/BodyAttachments/falleen/ridgedspine_hulk</Hulk>
				<Fat>Pawn/BodyAttachments/falleen/ridgedspine_fat</Fat>
			</bodyTypeGraphicPaths>
			<colorType>Skin</colorType>
			<parentTagDef>Body</parentTagDef>
			<rotDrawMode>Fresh, Rotting</rotDrawMode>
			<useSkinShader>true</useSkinShader>
			<useRottenColor>true</useRottenColor>
			<visibleFacing>
			  <li>East</li>
			  <li>North</li>
			  <li>West</li>
			</visibleFacing>
			<drawData>
			  <scaleOffsetByBodySize>true</scaleOffsetByBodySize>
			  <defaultData>
				<layer>20</layer>
			  </defaultData>
			</drawData>
		  </li>
		</renderNodeProperties>

	  </GeneDef>
	  
	  
	  
	  
	  <GeneDef MayRequire="OskarPotocki.VanillaFactionsExpanded.Core">
		<defName>guy762_butchergene_lizardskin</defName>
		<label>lizardskin</label>
		<description>Carriers of this gene yield lizardskin when their corpses are butchered.</description>
		<iconPath>Things/Item/Resource/Leather/Leather_b</iconPath>
		<iconColor>(101,116,58)</iconColor>
		<displayOrderInCategory>800</displayOrderInCategory>
		<displayCategory>guy762_SWparts_Category</displayCategory>
		<biostatCpx>1</biostatCpx>
		<!--biostatMet>3</biostatMet-->
		<selectionWeight>0</selectionWeight>
		<modExtensions>
			<li Class="VanillaGenesExpanded.GeneExtension"> 
				<customLeatherThingDef>Leather_Lizard</customLeatherThingDef>
				<!--customBloodThingDef>Filth_GreenBlood</customBloodThingDef>
				<customBloodIcon>UI/Icons/Medical/GreenBlood_BleedingIcon</customBloodIcon>
				<customBloodEffect>Damage_HitGreenFlesh</customBloodEffect>
				<customWoundsFromFleshtype>GreenWoundsFlesh</customWoundsFromFleshtype-->
			</li>
		</modExtensions>
	  </GeneDef>
	  
	  <GeneDef MayRequire="OskarPotocki.VanillaFactionsExpanded.Core">
		<defName>guy762_butchergene_insectmeat</defName>
		<label>insectoid</label>
		<description>Carriers of this gene yield insect meat when their corpses are butchered.</description>
		<iconPath>Things/Item/Resource/MeatFoodRaw/Meat_Insect/Meat_Insect_c</iconPath>
		<iconColor>(160,168,139)</iconColor>
		<displayOrderInCategory>600</displayOrderInCategory>
		<displayCategory>guy762_SWparts_Category</displayCategory>
		<biostatCpx>1</biostatCpx>
		<selectionWeight>0</selectionWeight>
		<exclusionTags>
			<li>Flesh</li>
			<li>Meat</li>
			<li>AG_Meat</li>
		</exclusionTags>
		<modExtensions>
			<li Class="VanillaGenesExpanded.GeneExtension">
				<customMeatThingDef>Meat_Megaspider</customMeatThingDef>
			</li>
		</modExtensions>
	  </GeneDef>
	  
	  
	  
	  
	  <GeneDef>
		  <defName>guy762_Body_gaunt</defName>
		  <label>gaunt body</label>
		  <labelShortAdj>gaunt body</labelShortAdj>
		  <description>Carriers of this gene have a thin, bony body.</description>
		  <exclusionTags>
			<li>BodyType</li>
		  </exclusionTags>
		  <biostatCpx>1</biostatCpx>
		  <selectionWeight>0</selectionWeight>
		  <displayCategory>guy762_SWparts_Category</displayCategory>
		  <displayOrderInCategory>801</displayOrderInCategory>
		  <iconPath>UI/Icons/Genes/Gene_GauntBody</iconPath>
		  <bodyType>Thin</bodyType>
		  <fur>guy762_FurDef_gaunt</fur>
		  <tattoosVisible>true</tattoosVisible>
		  <skinIsHairColor>false</skinIsHairColor>
		  <renderNodeProperties Inherit="False">
			<li>
			  <parentTagDef>Body</parentTagDef>
			  <useSkinShader>true</useSkinShader>
			  <debugLabel>Fur</debugLabel>
			  <nodeClass>BigAndSmall.PawnRenderNode_FurSkinClr</nodeClass>
			  <workerClass>PawnRenderNodeWorker_Fur</workerClass>
			  <baseLayer>5</baseLayer>
			  <rotDrawMode>Fresh, Rotting</rotDrawMode>
			  <colorType>Skin</colorType>
			</li>
		  </renderNodeProperties>
		</GeneDef>
		<FurDef>
		  <defName>guy762_FurDef_gaunt</defName>
		  <noGraphic>true</noGraphic>
		  <bodyTypeGraphicPaths>
			<Hulk>Things/Pawn/Humanlike/Bodies/Naked_Hulk</Hulk>

			<Male>Things/Pawn/Humanlike/Bodies/Naked_Male</Male>
			<Female>Things/Pawn/Humanlike/Bodies/Naked_Female</Female>
			
			<Fat>Things/Pawn/Humanlike/Bodies/Naked_Fat</Fat>
			<Thin>Pawn/BodyType/Gaunt</Thin><!---->
			
			<Child>Things/Pawn/Humanlike/Bodies/Naked_Child</Child>
			<Baby>Things/Pawn/Humanlike/Bodies/Naked_Child</Baby>
		  </bodyTypeGraphicPaths>
		</FurDef>
	  
	 

</Defs>